AUTHORS
CHANGELOG.md
LICENSE
MANIFEST.in
README.md
pyrenfe.py
setup.py
pyrenfe.egg-info/PKG-INFO
pyrenfe.egg-info/SOURCES.txt
pyrenfe.egg-info/dependency_links.txt
pyrenfe.egg-info/entry_points.txt
pyrenfe.egg-info/requires.txt
pyrenfe.egg-info/top_level.txt