Metadata-Version: 1.0
Name: pyrenfe
Version: 1.0
Summary: Train timetable checker (Renfe Cercanias, Spain)
Home-page: http://github.com/igalarzab/pyrenfe
Author: Jose Ignacio Galarza
Author-email: igalarzab@gmail.com
License: MIT
Keywords: timetable,train,cercanias,renfe,spain
Platform: UNKNOWN
Classifier: Development Status :: 5 - Production/Stable
Classifier: Environment :: Console
Classifier: License :: OSI Approved :: MIT License
Classifier: Operating System :: OS Independent
Classifier: Programming Language :: Python :: 2
Classifier: Programming Language :: Python :: 3
Classifier: Topic :: Utilities
